asyncio_paho/__init__.py
asyncio_paho/client.py
asyncio_paho/py.typed
asyncio_paho-0.6.0.dist-info/LICENSE
asyncio_paho-0.6.0.dist-info/METADATA
asyncio_paho-0.6.0.dist-info/WHEEL
asyncio_paho-0.6.0.dist-info/top_level.txt
asyncio_paho-0.6.0.dist-info/RECORD
