Metadata-Version: 2.1
Name: asyncio-paho
Version: 0.6.0
Summary: A Paho MQTT client supporting asyncio loop without additional setup.
Home-page: https://github.com/toreamun/asyncio-paho
Author: Tore Amundsen
Author-email: tore@amundsen.org
Keywords: paho,mqtt,asyncio
Classifier: Intended Audience :: Developers
Classifier: Programming Language :: Python :: 3
Classifier: License :: OSI Approved :: MIT License
Classifier: Operating System :: MacOS :: MacOS X
Classifier: Operating System :: Microsoft :: Windows
Classifier: Operating System :: POSIX
Classifier: Natural Language :: English
Classifier: Programming Language :: Python :: 3
Classifier: Programming Language :: Python :: 3.8
Classifier: Programming Language :: Python :: 3.9
Classifier: Programming Language :: Python :: 3.10
Requires-Python: >=3.8
License-File: LICENSE
Requires-Dist: paho-mqtt (~=1.6)
